odoo/addons/pos_multi_ean/README.rst
odoo/addons/pos_multi_ean/__init__.py
odoo/addons/pos_multi_ean/__manifest__.py
odoo/addons/pos_multi_ean/i18n/pos_multi_ean.pot
odoo/addons/pos_multi_ean/models/__init__.py
odoo/addons/pos_multi_ean/models/product.py
odoo/addons/pos_multi_ean/readme/CONFIGURE.rst
odoo/addons/pos_multi_ean/readme/CONTRIBUTORS.rst
odoo/addons/pos_multi_ean/readme/DESCRIPTION.rst
odoo/addons/pos_multi_ean/readme/USAGE.rst
odoo/addons/pos_multi_ean/static/description/icon.png
odoo/addons/pos_multi_ean/static/description/index.html
odoo/addons/pos_multi_ean/static/src/js/db.js
odoo/addons/pos_multi_ean/views/assets.xml
odoo12_addon_pos_multi_ean-12.0.1.0.1.dist-info/METADATA
odoo12_addon_pos_multi_ean-12.0.1.0.1.dist-info/WHEEL
odoo12_addon_pos_multi_ean-12.0.1.0.1.dist-info/top_level.txt
odoo12_addon_pos_multi_ean-12.0.1.0.1.dist-info/RECORD
